paymob/__init__.py
paymob/response_codes.py
paymob/accept/__init__.py
paymob/accept/accept_client.py
paymob/accept/config.py
paymob/accept/connection.py
paymob/accept/constants.py
paymob/accept/factories.py
paymob/accept/hmac_validator.py
paymob/accept/transaction.py
paymob/accept/utils.py
paymob/accept/callbacks/__init__.py
paymob/accept/callbacks/card_token_callback.py
paymob/accept/callbacks/delivery_status_callback.py
paymob/accept/callbacks/generic_callback.py
paymob/accept/callbacks/transaction_callback.py
paymob/data_classes/__init__.py
paymob/data_classes/response_feedback_dataclass.py
paymob/utils/__init__.py
paymob/utils/class_factory.py
tests/__init__.py
tests/utils.py
tests/accept/__init__.py
tests/accept/test_accept_client.py
tests/accept/test_accept_utils_class.py
tests/accept/test_connection.py
tests/accept/test_hmac_validator.py
tests/accept/test_transaction.py
tests/accept/callbacks/__init__.py
tests/accept/callbacks/test_accept_callback.py
tests/factories/__init__.py
tests/factories/response_factory.py
paymob_solutions-1.0.0.dist-info/METADATA
paymob_solutions-1.0.0.dist-info/WHEEL
paymob_solutions-1.0.0.dist-info/top_level.txt
paymob_solutions-1.0.0.dist-info/RECORD
